README.rst
setup.cfg
setup.py
scipyplot/__init__.py
scipyplot.egg-info/PKG-INFO
scipyplot.egg-info/SOURCES.txt
scipyplot.egg-info/dependency_links.txt
scipyplot.egg-info/requires.txt
scipyplot.egg-info/top_level.txt
scipyplot.egg-info/zip-safe
scipyplot/log/__init__.py
scipyplot/log/msg.py
scipyplot/log/status.py
scipyplot/plot/__init__.py
scipyplot/plot/gauss_1D.py
scipyplot/plot/save2file.py
scipyplot/plot/surface.py
scipyplot/plot/training_process.py
scipyplot/plot/trajectory.py
scipyplot/plot/utils/__init__.py
scipyplot/plot/utils/interactivePlot.py
scipyplot/plot/utils/niceFigure.py
scipyplot/stats/__init__.py
scipyplot/stats/distribution.py
scipyplot/utils/RGB2video.py
scipyplot/utils/__init__.py
scipyplot/utils/bounds.py
scipyplot/utils/indent.py
scipyplot/utils/niceFigure.py
test/__init__.py
test/test_gauss_1D.py
test/test_rplot.py
test/test_rplot_data.py