Metadata-Version: 1.1
Name: scipyplot
Version: 0.0.3
Summary: A Python Toolbox for Creating Scientific Article Figures
Home-page: https://github.com/robertocalandra/scipyplot
Author: Roberto Calandra
Author-email: roberto.calandra@berkeley.edu
License: LICENSE.txt
Keywords: visualization,science
Platform: UNKNOWN
Classifier: Programming Language :: Python :: 2
Classifier: Programming Language :: Python :: 3
